ajax_cbv/__init__.py
ajax_cbv/apps.py
ajax_cbv/mixins.py
ajax_cbv/views.py
ajax_cbv/static/ajax_cbv/forms.jquery.js
ajax_cbv/static/ajax_cbv/partials.jquery.js
ajax_cbv/tests/__init__.py
ajax_cbv/tests/test_mixins.py
ajax_cbv/tests/test_views.py
django_ajax_cbv-0.1.1.dist-info/DESCRIPTION.rst
django_ajax_cbv-0.1.1.dist-info/METADATA
django_ajax_cbv-0.1.1.dist-info/RECORD
django_ajax_cbv-0.1.1.dist-info/WHEEL
django_ajax_cbv-0.1.1.dist-info/metadata.json
django_ajax_cbv-0.1.1.dist-info/top_level.txt
